{
  "table_index": ["t1","t2","t3","t4","t5","t6","t7"],
  "images": {
    "t1": ["应收账款和合同资产占总资产的比率"],
    "t2": ["利息收入占平均货币资金的比率"],
    "t3": ["利息支出占净利润的比率"],
    "t4": ["预付款项和其他应收款占总资产的比率"],
    "t5": ["在建工程占总资产的比例"],
    "t6": ["存货和应收账款情况"],
    "t7": ["商誉占总资产的比例"]
  },
  "titles": {
    "t1": "一.假销售：应收账款和合同资产占比异常",
    "t2": "二.假存款：利息收入异常",
    "t3": "三.假存款：利息支出异常",
    "t4": "四.假购买：预付款项和其他应收款占比异常",
    "t5": "五.假工程：在建工程占比异常",
    "t6": "六.假库存：存货占比异常",
    "t7": "七.假收购：商誉占比异常"
  },
  "tables_fields": {
    "t1": {
      "columns": ["合同资产(元)", "应收账款(元)", "应收账款+合同资产", "资产合计(元)", "(应收账款+合同资产)占总资产的比率"],
      "auto": ["合同资产(元)", "应收账款(元)", "资产合计(元)"],
      "plot": [{"columns": "(应收账款+合同资产)占总资产的比率" }]
    },
    "t2": {
      "columns": ["利息收入(元)", "货币资金(元)", "平均货币资金", "利息收入占平均货币资金的比率"],
      "auto": ["利息收入(元)", "货币资金(元)"],
      "plot": [{"columns": "利息收入占平均货币资金的比率"}]
    },
    "t3": {
      "columns": ["其中：利息费用(元)", "五、净利润(元)", "利息费用占净利润的比率"],
      "auto": ["其中：利息费用(元)", "五、净利润(元)"],
      "plot": [{"columns": "利息费用占净利润的比率"}]
    },
    "t4": {
      "columns": ["预付款项(元)", "其他应收款合计(元)", "资产合计(元)", "预付款项和其他应收款占总资产的比率"],
      "auto": ["预付款项(元)", "其他应收款合计(元)", "资产合计(元)"],
      "plot": [{"columns": "预付款项和其他应收款占总资产的比率"}]
    },
    "t5": {
      "columns": ["在建工程合计(元)", "资产合计(元)", "在建工程占总资产的比率"],
      "auto": ["在建工程合计(元)", "资产合计(元)"],
      "plot": [{"columns": "在建工程占总资产的比率"}]
    },
    "t6": {
      "columns": ["存货(元)", "资产合计(元)", "存货占总资产的比率"],
      "auto": ["存货(元)", "资产合计(元)"],
      "plot": [{"columns": "存货占总资产的比率"}]
    },
    "t7": {
      "columns": ["商誉(元)", "资产合计(元)", "商誉占总资产的比率"],
      "auto": ["商誉(元)", "资产合计(元)"],
      "plot": [{"columns": "商誉占总资产的比率"}]
    }
  }
}